{"type": "FeatureCollection","features":[{"type":"Feature","geometry":{"type":"Point","coordinates":[136.185000,36.085556]},"properties":{"一級水系":"","所管機関名":"福井河川国道事務所","水系名称":"九頭竜川","河口からの":18100,"河川名_観":"日野川_深谷","河川名称":"日野川","河川番号":86068016,"観測所位置":"","観測所名称":"深谷","観測所所在":"福井県福井市三ツ屋町"}},{"type":"Feature","geometry":{"type":"Point","coordinates":[136.208333,36.102500]},"properties":{"一級水系":"","所管機関名":"福井河川国道事務所","水系名称":"九頭竜川","河口からの":18200,"河川名_観":"九頭竜川_中角","河川名称":"九頭竜川","河川番号":86068001,"観測所位置":"","観測所名称":"中角(副)","観測所所在":"福井県福井市中角町"}},{"type":"Feature","geometry":{"type":"Point","coordinates":[136.288889,36.020556]},"properties":{"一級水系":"","所管機関名":"福井河川国道事務所","水系名称":"九頭竜川","河口からの":31200,"河川名_観":"足羽川_天神橋","河川名称":"足羽川","河川番号":86068123,"観測所位置":"天神橋地点","観測所名称":"天神橋(副)","観測所所在":"福井県福井市脇三ケ町"}}]}